LICENSE
MANIFEST.in
README.md
setup.py
src/ea/__init__.py
src/ea/sutadapters/__init__.py
src/ea/sutadapters/CLI/__init__.py
src/ea/sutadapters/CLI/client.py
src/ea/sutadapters/CLI/codec_term.py
src/ea/sutadapters/CLI/templates.py
src/ea/sutadapters/CLI/templates_term.py
src/ea/sutadapters/CLI/terminal_ssh.py
src/ea/sutadapters/CLI/deps/pip_list.txt
src/ea/sutadapters/CLI/deps/yum_list.txt
src/ea/var/tests/1/actions/ssh/send_commands.yml
src/ea/var/tests/1/actions/ssh/send_expect.yml
src/ea/var/tests/1/deprecated/Samples/Adapter_CLI/001_Agent_Sftp.tpx
src/ea/var/tests/1/deprecated/Samples/Adapter_CLI/01_CLI.tsx
src/ea/var/tests/1/deprecated/Samples/Adapter_CLI/02_SFTP.tsx
src/ea/var/tests/1/workflows/ssh/ssh_commands.yml
src/ea/var/tests/1/workflows/ssh/ssh_expect.yml
src/extensiveautomation_plugin_cli.egg-info/PKG-INFO
src/extensiveautomation_plugin_cli.egg-info/SOURCES.txt
src/extensiveautomation_plugin_cli.egg-info/dependency_links.txt
src/extensiveautomation_plugin_cli.egg-info/requires.txt
src/extensiveautomation_plugin_cli.egg-info/top_level.txt